cricket_package/__init__.py
cricket_package/cricket.py
hand_cricket-0.0.3.dist-info/LICENSE
hand_cricket-0.0.3.dist-info/METADATA
hand_cricket-0.0.3.dist-info/WHEEL
hand_cricket-0.0.3.dist-info/top_level.txt
hand_cricket-0.0.3.dist-info/RECORD
